odoo10_addon_account_asset_maintenance-10.0.1.0.0-py2.7-nspkg.pth
odoo/addons/account_asset_maintenance/README.rst
odoo/addons/account_asset_maintenance/__init__.py
odoo/addons/account_asset_maintenance/__manifest__.py
odoo/addons/account_asset_maintenance/i18n/es.po
odoo/addons/account_asset_maintenance/models/__init__.py
odoo/addons/account_asset_maintenance/models/account_asset_asset.py
odoo/addons/account_asset_maintenance/models/account_asset_category.py
odoo/addons/account_asset_maintenance/models/account_invoice.py
odoo/addons/account_asset_maintenance/models/maintenance_equipment.py
odoo/addons/account_asset_maintenance/tests/__init__.py
odoo/addons/account_asset_maintenance/tests/test_account_asset_maintenance.py
odoo/addons/account_asset_maintenance/views/account_asset_asset_views.xml
odoo/addons/account_asset_maintenance/views/account_asset_category_views.xml
odoo/addons/account_asset_maintenance/views/account_invoice_views.xml
odoo/addons/account_asset_maintenance/views/maintenance_equipment_views.xml
odoo10_addon_account_asset_maintenance-10.0.1.0.0.dist-info/DESCRIPTION.rst
odoo10_addon_account_asset_maintenance-10.0.1.0.0.dist-info/METADATA
odoo10_addon_account_asset_maintenance-10.0.1.0.0.dist-info/RECORD
odoo10_addon_account_asset_maintenance-10.0.1.0.0.dist-info/WHEEL
odoo10_addon_account_asset_maintenance-10.0.1.0.0.dist-info/metadata.json
odoo10_addon_account_asset_maintenance-10.0.1.0.0.dist-info/namespace_packages.txt
odoo10_addon_account_asset_maintenance-10.0.1.0.0.dist-info/top_level.txt
